scribus/__init__.py
scribus/cli.py
scribus-0.1.3.dist-info/METADATA
scribus-0.1.3.dist-info/WHEEL
scribus-0.1.3.dist-info/entry_points.txt
scribus-0.1.3.dist-info/top_level.txt
scribus-0.1.3.dist-info/RECORD
