Metadata-Version: 2.1
Name: scribus
Version: 0.1.3
Summary: A helper for handwriting import
Home-page: https://gitlab.com/plup/scribus
Author: Plup
Author-email: plup@plup.io
License: ISC
Platform: UNKNOWN
Classifier: Programming Language :: Python :: 3
Classifier: Operating System :: OS Independent
Requires-Python: >=3.8
Requires-Dist: click
